lhcb_pre_commit_hooks/__init__.py
lhcb_pre_commit_hooks/constants/__init__.py
lhcb_pre_commit_hooks/constants/license_constants.py
lhcb_pre_commit_hooks/hooks/__init__.py
lhcb_pre_commit_hooks/hooks/check_for_license_file.py
lhcb_pre_commit_hooks/utils/__init__.py
lhcb_pre_commit_hooks/utils/file_utils.py
lhcb_pre_commit_hooks/utils/string_utils.py
lhcb_hooks-0.0.1.dist-info/METADATA
lhcb_hooks-0.0.1.dist-info/WHEEL
lhcb_hooks-0.0.1.dist-info/entry_points.txt
lhcb_hooks-0.0.1.dist-info/top_level.txt
lhcb_hooks-0.0.1.dist-info/RECORD
